gradio_multichat/__init__.py
gradio_multichat/multichat.py
gradio_multichat/templates/component/index.js
gradio_multichat/templates/component/style.css
gradio_multichat/templates/component/assets/worker-43d19264.js
gradio_multichat-0.0.6.dist-info/METADATA
gradio_multichat-0.0.6.dist-info/WHEEL
gradio_multichat-0.0.6.dist-info/licenses/LICENSE
gradio_multichat-0.0.6.dist-info/RECORD
