Metadata-Version: 2.1
Name: gradio_multichat
Version: 0.0.6
Summary: A Gradio Chatbot variant for handling multiple characters with customizable profiles, pictures, and CSS. Ideal for diverse tasks like multi-entity conversations and role-playing scenarios.
Author: gr1336
License-Expression: MIT
License-File: LICENSE
Keywords: actors,agents,characters,chat,chatbot,entities,gradio,gradio-custom-component,gradio-template-Chatbot,multi,multiple,roleplay,roleplaying
Classifier: Development Status :: 3 - Alpha
Classifier: License :: OSI Approved :: Apache Software License
Classifier: Operating System :: OS Independent
Classifier: Programming Language :: Python :: 3
Classifier: Programming Language :: Python :: 3 :: Only
Classifier: Programming Language :: Python :: 3.8
Classifier: Programming Language :: Python :: 3.9
Classifier: Programming Language :: Python :: 3.10
Classifier: Programming Language :: Python :: 3.11
Classifier: Topic :: Scientific/Engineering
Classifier: Topic :: Scientific/Engineering :: Artificial Intelligence
Classifier: Topic :: Scientific/Engineering :: Visualization
Requires-Python: >=3.8
Requires-Dist: gradio<5.0,>=4.0
Provides-Extra: dev
Requires-Dist: build; extra == 'dev'
Requires-Dist: twine; extra == 'dev'
